glam/client.py
glam/mint/__init__.py
glam/mint/program_id.py
glam/mint/accounts/__init__.py
glam/mint/accounts/globalConfig.py
glam/mint/accounts/requestQueue.py
glam/mint/accounts/stateAccount.py
glam/mint/errors/__init__.py
glam/mint/errors/glamMint.py
glam/mint/instructions/__init__.py
glam/mint/instructions/burnTokens.py
glam/mint/instructions/cancel.py
glam/mint/instructions/claim.py
glam/mint/instructions/claimFees.py
glam/mint/instructions/closeMint.py
glam/mint/instructions/crystallizeFees.py
glam/mint/instructions/emergencyUpdateMint.py
glam/mint/instructions/forceTransferTokens.py
glam/mint/instructions/fulfill.py
glam/mint/instructions/initializeMint.py
glam/mint/instructions/mintTokens.py
glam/mint/instructions/priceDriftUsers.py
glam/mint/instructions/priceDriftVaultDepositors.py
glam/mint/instructions/priceKaminoObligations.py
glam/mint/instructions/priceKaminoVaultShares.py
glam/mint/instructions/priceVaultTokens.py
glam/mint/instructions/queuedRedeem.py
glam/mint/instructions/queuedSubscribe.py
glam/mint/instructions/setMintPolicy.py
glam/mint/instructions/setProtocolFees.py
glam/mint/instructions/setTokenAccountsStates.py
glam/mint/instructions/subscribe.py
glam/mint/instructions/updateMint.py
glam/mint/instructions/updateMintApplyTimelock.py
glam/mint/instructions/validateAum.py
glam/mint/shared/__init__.py
glam/mint/shared/extension.py
glam/mint/types/__init__.py
glam/mint/types/accountType.py
glam/mint/types/accruedFees.py
glam/mint/types/assetMeta.py
glam/mint/types/aumRecord.py
glam/mint/types/createdModel.py
glam/mint/types/delegateAcl.py
glam/mint/types/engineField.py
glam/mint/types/engineFieldName.py
glam/mint/types/engineFieldValue.py
glam/mint/types/entryExitFees.py
glam/mint/types/feeParams.py
glam/mint/types/feeStructure.py
glam/mint/types/hurdleType.py
glam/mint/types/integrationAcl.py
glam/mint/types/integrationPermissions.py
glam/mint/types/managementFee.py
glam/mint/types/mintModel.py
glam/mint/types/noticePeriodType.py
glam_sdk-0.1.6.dist-info/licenses/LICENSE
glam_sdk-0.1.6.dist-info/METADATA
glam_sdk-0.1.6.dist-info/WHEEL
glam_sdk-0.1.6.dist-info/top_level.txt
glam_sdk-0.1.6.dist-info/RECORD
