Metadata-Version: 2.4
Name: glam-sdk
Version: 0.1.6
Summary: Python SDK for GLAM protocol
Author-email: GLAM Systems <yuru@glam.systems>
License: Apache-2.0
Project-URL: Homepage, https://github.com/glamsystems/glam-sdk-py
Project-URL: Documentation, https://docs.glam.systems
Project-URL: Repository, https://github.com/glamsystems/glam-sdk-py
Project-URL: Issues, https://github.com/glamsystems/glam-sdk-py/issues
Keywords: solana,blockchain,glam,sdk
Classifier: Development Status :: 3 - Alpha
Classifier: Intended Audience :: Developers
Classifier: Programming Language :: Python :: 3
Classifier: Programming Language :: Python :: 3.8
Classifier: Programming Language :: Python :: 3.9
Classifier: Programming Language :: Python :: 3.10
Classifier: Programming Language :: Python :: 3.11
Classifier: Programming Language :: Python :: 3.12
Requires-Python: >=3.8
License-File: LICENSE
Requires-Dist: anchorpy>=0.21.0
Requires-Dist: solana>=0.36.0
Requires-Dist: solders>=0.26.0
Provides-Extra: dev
Requires-Dist: pytest>=7.0; extra == "dev"
Requires-Dist: pytest-asyncio>=0.21.0; extra == "dev"
Requires-Dist: pytest-xprocess>=0.18.0; extra == "dev"
Requires-Dist: mypy>=1.0; extra == "dev"
Requires-Dist: ruff>=0.1.0; extra == "dev"
Dynamic: license-file
